boxes_tui/__init__.py
boxes_tui/tui.py
boxes_tui-2.2.1.dist-info/METADATA
boxes_tui-2.2.1.dist-info/WHEEL
boxes_tui-2.2.1.dist-info/licenses/LICENSE
boxes_tui-2.2.1.dist-info/RECORD
