Metadata-Version: 2.4
Name: boxes-tui
Version: 2.2.1
Summary: A collection of tools for python TUIs
Project-URL: Homepage, https://github.com/IamLegende7/boxes-tui
Project-URL: Issues, https://github.com/IamLegende7/boxes-tui/issues
Author: Legende_7
License-Expression: BSD-2-Clause
License-File: LICENSE
Classifier: Operating System :: OS Independent
Classifier: Programming Language :: Python :: 3
Requires-Python: >=3.9
